{
  "os": "Windows-10-10.0.26200-SP0",
  "python": "CPython 3.10.11",
  "startedAt": "2026-06-14T13:15:15.583916Z",
  "program": "c:\\Users\\ASUS\\OneDrive\\Desktop\\lung_disease_digonosis\\notebook\\Experiment.ipynb",
  "codePath": "c:\\Users\\ASUS\\OneDrive\\Desktop\\lung_disease_digonosis\\notebook\\Experiment.ipynb",
  "codePathLocal": "Experiment.ipynb",
  "git": {
    "remote": "https://github.com/vicky060403/Lungs_Disease_Digonosis.git",
    "commit": "26a5668bc0d8588acd8215cc9a54534baa965963"
  },
  "email": "vk0099678@gmail.com",
  "root": "c:\\Users\\ASUS\\OneDrive\\Desktop\\lung_disease_digonosis\\notebook",
  "host": "Vickypandey123",
  "executable": "c:\\Users\\ASUS\\OneDrive\\Desktop\\lung_disease_digonosis\\.venv\\Scripts\\python.exe",
  "cpu_count": 8,
  "cpu_count_logical": 16,
  "disk": {
    "/": {
      "total": "194470285312",
      "used": "153022922752"
    }
  },
  "memory": {
    "total": "16541728768"
  },
  "writerId": "55pmvx7ikke4kmqgka4ta5suo9o44l8d"
}